{
  "string": [
    { "name": "account_default_user", "value": "User" },
    { "name": "account_delete", "value": "Delete account" },
    { "name": "account_delete_confirmation", "value": "Are you sure you want to delete this account?" },
    { "name": "account_delete_success", "value": "Account deleted" },
    { "name": "account_login_account", "value": "Sign-in account" },
    { "name": "account_logout", "value": "Sign out" },
    { "name": "account_logout_success", "value": "Signed out" },
    { "name": "account_personal_info", "value": "Personal information" },
    { "name": "account_profile_complete", "value": "Profile complete" },
    { "name": "account_profile_incomplete", "value": "Profile incomplete" },
    { "name": "account_section", "value": "Account" },
    { "name": "account_title", "value": "Me" },
    { "name": "auth_account", "value": "Account" },
    { "name": "auth_account_login", "value": "Account sign in" },
    { "name": "auth_account_placeholder", "value": "Enter a phone number or email" },
    { "name": "auth_agree_and_continue", "value": "Agree and continue" },
    { "name": "auth_china_dialing_code", "value": "+86" },
    { "name": "auth_clear_input", "value": "Clear input" },
    { "name": "auth_code_help", "value": "Didn't receive a code?" },
    { "name": "auth_confirm_new_password_placeholder", "value": "Re-enter the new password" },
    { "name": "auth_confirm_password_placeholder", "value": "Re-enter the password" },
    { "name": "auth_email_placeholder", "value": "Enter your email" },
    { "name": "auth_email_register", "value": "Email registration" },
    { "name": "auth_feedback", "value": "◔ Feedback" },
    { "name": "auth_find_password", "value": "Reset password" },
    { "name": "auth_forgot_password", "value": "Forgot password?" },
    { "name": "auth_get_code", "value": "Get code" },
    { "name": "auth_got_it", "value": "Got it" },
    { "name": "auth_hide_password", "value": "Hide password" },
    { "name": "auth_login", "value": "Sign in" },
    { "name": "auth_login_success", "value": "Signed in" },
    { "name": "auth_logo", "value": "COROS Logo" },
    { "name": "auth_new_password_placeholder", "value": "Enter a new password" },
    { "name": "auth_next_step", "value": "Next" },
    { "name": "auth_password", "value": "Password" },
    { "name": "auth_password_rule", "value": "6-20 characters with letters and numbers" },
    { "name": "auth_password_updated", "value": "Password updated" },
    { "name": "auth_phone_placeholder", "value": "Enter a phone number" },
    { "name": "auth_phone_register", "value": "Phone registration" },
    { "name": "auth_privacy_policy", "value": "Privacy Policy" },
    { "name": "auth_privacy_policy_link", "value": "Privacy Policy" },
    { "name": "auth_processing", "value": "Processing" },
    { "name": "auth_read_terms", "value": "Read and agree to the following terms:" },
    { "name": "auth_register", "value": "Sign up" },
    { "name": "auth_register_success", "value": "Registration complete" },
    { "name": "auth_resend", "value": "Resend" },
    { "name": "auth_resend_countdown", "value": "(%d s)" },
    { "name": "auth_send_code", "value": "Send verification code" },
    { "name": "auth_service_terms", "value": "Terms of Service" },
    { "name": "auth_service_terms_link", "value": "Terms of Service" },
    { "name": "auth_session_expired", "value": "Your session expired. Sign in again" },
    { "name": "auth_set_login_password", "value": "Set sign-in password" },
    { "name": "auth_set_new_password", "value": "Set new password" },
    { "name": "auth_show_password", "value": "Show password" },
    { "name": "auth_submit_failed", "value": "Submission failed. Try again" },
    { "name": "auth_terms_inline_prefix", "value": "I have read and agree to COROS's " },
    { "name": "auth_terms_joiner", "value": " and " },
    { "name": "auth_third_party_account", "value": "Third-party account" },
    { "name": "auth_unavailable", "value": "Sorry, this feature is not available yet" },
    { "name": "auth_verification_code", "value": "Enter verification code" },
    { "name": "auth_verification_sent_email", "value": "A verification code was sent to %s. It is valid for 60 seconds" },
    { "name": "auth_verification_sent_phone", "value": "A verification code was sent to +86-%s. It is valid for 60 seconds" },
    { "name": "auth_version", "value": "V4.8.1.14" },
    { "name": "business_welcome_back", "value": "Welcome back, %s" },
    { "name": "language_chinese", "value": "简体中文" },
    { "name": "language_english", "value": "English" },
    { "name": "language_select_title", "value": "Choose a language" },
    { "name": "language_switch", "value": "Switch language" },
    { "name": "common_back", "value": "‹" },
    { "name": "common_cancel", "value": "Cancel" },
    { "name": "common_china", "value": "China" },
    { "name": "common_complete", "value": "Done" },
    { "name": "common_confirm", "value": "Confirm" },
    { "name": "common_female", "value": "Female" },
    { "name": "common_japan", "value": "Japan" },
    { "name": "common_male", "value": "Male" },
    { "name": "common_next", "value": "›" },
    { "name": "common_not_set", "value": "Not set" },
    { "name": "common_save", "value": "Save" },
    { "name": "common_united_kingdom", "value": "United Kingdom" },
    { "name": "common_united_states", "value": "United States" },
    { "name": "profile_add_avatar", "value": "Add avatar" },
    { "name": "profile_album", "value": "Photo library" },
    { "name": "profile_avatar_selection_failed", "value": "Failed to select avatar" },
    { "name": "profile_birth_date", "value": "Date of birth" },
    { "name": "profile_camera_pending", "value": "Camera integration is not available yet" },
    { "name": "profile_close", "value": "Close" },
    { "name": "profile_completion_description", "value": "Provide the following information to help us make more accurate sports science predictions." },
    { "name": "profile_completion_title", "value": "Complete your profile" },
    { "name": "profile_country_region", "value": "Country or region" },
    { "name": "profile_date_day_suffix", "value": " day" },
    { "name": "profile_date_month_suffix", "value": " mo" },
    { "name": "profile_date_year_suffix", "value": " yr" },
    { "name": "profile_edit_username", "value": "Edit username" },
    { "name": "profile_fill_in", "value": "Fill in" },
    { "name": "profile_gender", "value": "Gender" },
    { "name": "profile_height", "value": "Height" },
    { "name": "profile_height_picker", "value": "Height (cm)" },
    { "name": "profile_measurement", "value": "Units" },
    { "name": "profile_personal_info", "value": "Personal information" },
    { "name": "profile_phone", "value": "Phone" },
    { "name": "profile_phone_placeholder", "value": "Enter a phone number" },
    { "name": "profile_saved", "value": "Profile saved" },
    { "name": "profile_take_photo", "value": "Take photo" },
    { "name": "profile_unit_imperial", "value": "Imperial (mi/ft/in/lb)" },
    { "name": "profile_unit_metric", "value": "Metric (km/m/cm/kg)" },
    { "name": "profile_username", "value": "Username" },
    { "name": "profile_username_placeholder", "value": "Enter a username" },
    { "name": "profile_weight", "value": "Weight" },
    { "name": "profile_weight_picker", "value": "Weight (kg)" },
    { "name": "health_add", "value": "Add" },
    { "name": "health_calendar", "value": "Calendar" },
    { "name": "health_card_body_management_title", "value": "Body Management" },
    { "name": "health_card_cycling_ability_title", "value": "Cycling FTP" },
    { "name": "health_card_health_check_title", "value": "Health Check" },
    { "name": "health_card_heart_rate_title", "value": "Heart Rate" },
    { "name": "health_card_hrv_assessment_title", "value": "HRV Assessment" },
    { "name": "health_card_recovery_title", "value": "Recovery" },
    { "name": "health_card_resting_heart_rate_title", "value": "Resting Heart Rate" },
    { "name": "health_card_running_ability_title", "value": "Running Ability" },
    { "name": "health_card_sleep_title", "value": "Sleep" },
    { "name": "health_card_stress_title", "value": "Stress" },
    { "name": "health_card_today_activity_title", "value": "Today Activity" },
    { "name": "health_card_training_assessment_title", "value": "Training Assessment" },
    { "name": "health_card_training_load_title", "value": "Weekly Load" },
    { "name": "health_card_weekly_plan_title", "value": "Weekly Plan" },
    { "name": "health_data_corrupted", "value": "Data is corrupted. Pull down to sync again" },
    { "name": "health_data_syncing", "value": "Syncing data" },
    { "name": "health_data_unavailable", "value": "Health data is temporarily unavailable" },
    { "name": "health_demo_date", "value": "Wed, Jul 15" },
    { "name": "health_edit_cards", "value": "Edit Cards" },
    { "name": "health_manage_cards", "value": "Manage card order (show at least 3)" },
    { "name": "health_minimum_cards", "value": "Show at least three daily data cards" },
    { "name": "health_more_daily_data", "value": "More Daily Data" },
    { "name": "health_pending_feature", "value": "%s will be available later" },
    { "name": "health_remove", "value": "Remove" },
    { "name": "health_restore_defaults", "value": "Restore Default Data" },
    { "name": "health_scenario_abnormal", "value": "Abnormal Data" },
    { "name": "health_scenario_all_empty", "value": "All Data Empty" },
    { "name": "health_scenario_normal", "value": "Normal Data" },
    { "name": "health_scenario_partial_missing", "value": "Some Data Missing" },
    { "name": "health_scenario_read_failure", "value": "Corrupted Data" },
    { "name": "health_select_scenario", "value": "Select Data Scenario" },
    { "name": "health_sport_device", "value": "Sports Device" },
    { "name": "health_summary_activity_empty", "value": "No activity data yet today" },
    { "name": "health_summary_activity_normal", "value": "%s steps · %s Kcal · %s min" },
    { "name": "health_summary_body_empty", "value": "Weight --- kg · Main training areas this week" },
    { "name": "health_summary_body_normal", "value": "Weight %s kg · BMI %s" },
    { "name": "health_summary_body_risk", "value": "Weight %s kg · BMI %s. Review body health" },
    { "name": "health_summary_cycling_empty", "value": "Connect a power meter and complete a steady ride over 20 min" },
    { "name": "health_summary_cycling_normal", "value": "FTP %sW · Score %s" },
    { "name": "health_summary_cycling_risk", "value": "FTP %sW · Score %s. Add more cycling training" },
    { "name": "health_summary_health_check_empty", "value": "Use Health Check on your watch to collect data" },
    { "name": "health_summary_health_check_normal", "value": "Overall score %s · Measured %s days ago" },
    { "name": "health_summary_health_check_risk", "value": "Overall score %s, measured %s days ago. Measure again" },
    { "name": "health_summary_heart_rate_empty", "value": "Wear your watch to record heart-rate data" },
    { "name": "health_summary_heart_rate_normal", "value": "Resting %s bpm · Current %s bpm" },
    { "name": "health_summary_heart_rate_risk", "value": "Resting %s bpm · Current %s bpm. Heart rate is high" },
    { "name": "health_summary_hrv_empty", "value": "Wear your watch while sleeping to collect data" },
    { "name": "health_summary_hrv_normal", "value": "HRV %s ms · Status %s" },
    { "name": "health_summary_hrv_risk", "value": "HRV %s ms · Status %s. Pay attention to recovery" },
    { "name": "health_summary_recovery_empty", "value": "Record a workout with your watch to assess recovery" },
    { "name": "health_summary_recovery_normal", "value": "Recovery score %s. About %s hours to recover" },
    { "name": "health_summary_recovery_risk", "value": "Recovery is low. Reduce training intensity" },
    { "name": "health_summary_resting_hr_empty", "value": "Wear your watch while sleeping or run a resting heart-rate test" },
    { "name": "health_summary_resting_hr_normal", "value": "%s bpm" },
    { "name": "health_summary_resting_hr_risk", "value": "%s bpm, above the normal range" },
    { "name": "health_summary_running_empty", "value": "Record an outdoor run longer than 25 min" },
    { "name": "health_summary_running_normal", "value": "VO2Max %s · Score %s" },
    { "name": "health_summary_running_risk", "value": "VO2Max %s · Score %s. Add more aerobic training" },
    { "name": "health_summary_sleep_empty", "value": "No sleep data from last night" },
    { "name": "health_summary_sleep_normal", "value": "Last night: %s hr %s min · Quality %s" },
    { "name": "health_summary_sleep_risk", "value": "Sleep quality is low. Make time to rest today" },
    { "name": "health_summary_stress_empty", "value": "Wear your watch or run Health Check to measure stress" },
    { "name": "health_summary_stress_normal", "value": "Stress level %s · Status %s" },
    { "name": "health_summary_stress_risk", "value": "Stress level %s · Status %s. Relax and rest" },
    { "name": "health_summary_training_assessment_empty", "value": "Training volume will be assessed 7 days after your first workout" },
    { "name": "health_summary_training_assessment_normal", "value": "Score %s · Trend %s" },
    { "name": "health_summary_training_assessment_risk", "value": "Training volume is low. Score %s · Trend %s" },
    { "name": "health_summary_training_load_empty", "value": "No training-load data" },
    { "name": "health_summary_training_load_normal", "value": "Weekly load %s · Recommended %s-%s" },
    { "name": "health_summary_training_load_risk", "value": "Load %s exceeds the recommended range. Schedule recovery" },
    { "name": "health_summary_weekly_custom", "value": "%s" },
    { "name": "health_summary_weekly_empty", "value": "No plan this week" },
    { "name": "health_summary_weekly_ready", "value": "Weekly training plan ready · %s min" },
    { "name": "health_today", "value": "Today" },
    { "name": "health_unit_calories", "value": "Kcal" },
    { "name": "health_unit_minutes", "value": "Min" },
    { "name": "health_unit_steps", "value": "Steps" },
    { "name": "legal_privacy_body", "value": "Demo translation notice: This English text is provided only for this non-production demo and is not a formally reviewed legal document.\n\nLast updated: December 24, 2025\n\nIntroduction\n\nGuangdong COROS Sports Technology Co., Ltd. (“**COROS**” or “**we**”) places great importance on the **privacy and personal information protection** of users (“**you**”). We will make every reasonable effort to protect your personal information in accordance with applicable laws and regulations.\n\nThis Personal Information Protection Policy (“**Policy**”) applies when you use our products and services through the COROS website, the **COROS App**, and other COROS products and services.\n\nThis Policy explains how we **collect, store, use, provide, and delete** your information and describes your rights. Please read and understand this Policy carefully, especially the provisions concerning **sensitive personal information, system permissions, third-party sharing, and account deletion**.\n\n## 1. How We Collect and Use Personal Information\n\n1. We describe the **types of personal information** collected and their uses so that you can understand the categories of information processed by each feature, the purposes of processing, and the processing methods.\n\n2. To provide workout records, device connections, account sign-in, security, and customer support, we may process account information, device information, workout data, network status, and necessary log information **after receiving authorization**.\n\n## 2. How We Provide and Share Personal Information\n\n**Unless you consent**, we will not voluntarily provide your personal information to third parties outside COROS. If external provision is necessary, or if you ask us to provide information to a third party, we will obtain your consent directly unless otherwise required by law.\n\n## 3. How You Can Manage Personal Information\n\nYou may use the methods described in this Policy to **access, update, copy, or delete** your personal information, withdraw consent, delete your account, or submit complaints and reports. We will process requests within the periods required by applicable laws and regulations.\n\n## 4. System Permissions and Sensitive Information\n\nTo collect information under this Policy, provide and improve services, and protect account security, we may request relevant **system permissions**. Sensitive permissions, such as location, **are not enabled by default** and are used only within the scope to which you explicitly consent.\n\n## 5. How This Policy Is Updated\n\nWe will continue to protect your personal information and may update this Policy because of product changes, laws, regulations, or regulatory requirements. If a **material change** occurs, we will notify you in a reasonable manner." },
    { "name": "legal_service_terms_body", "value": "Demo translation notice: This English text is provided only for this non-production demo and is not a formally reviewed legal document.\n\nLast updated: September 4, 2023\n\nSpecial Notice:\n\nThis COROS User Agreement (“**Agreement**”) is entered into between you (“**User**”) and Guangdong COROS Sports Technology Co., Ltd. (“**COROS**” or “**we**”) concerning your use of the COROS website, the **COROS App**, and other COROS products and services (collectively, “**COROS Products and Services**”).\n\nPlease **read and understand this Agreement carefully**, especially provisions shown in bold that exempt or limit COROS liability. You may accept or reject this Agreement. **Unless you accept all terms, you may not register, sign in to, or use COROS Products and Services.**\n\nWhen you click “I have read and agree to all terms of this Agreement” and complete registration, you are considered to have fully read, understood, and accepted all content of this Agreement at that time. **This Agreement then becomes effective between you and COROS**, and you agree to be bound by its terms.\n\nThis Agreement includes agreements, rules, announcements, or notices that we have published or may change or publish in the future. Unless the law or this Agreement provides otherwise, such content **becomes effective when published** and forms an inseparable part of this Agreement without separate notice.\n\nIf you disagree with this Agreement or with any agreement, rule, announcement, or notice published after your acceptance, you should **sign out, delete your account, and stop using COROS Products and Services**. Continued use means that you continue to accept and comply with all content of this Agreement.\n\n## 1. Scope of Services\n\n1. We grant you a **personal, non-transferable, non-sublicensable, non-exclusive, and revocable** license to use COROS Products and Services.\n\n2. You must use the products and services in accordance with laws, this Agreement, and rules published by COROS. You **may not use the services for unlawful activities or to infringe the lawful rights of others**.\n\n3. We may **adjust, update, or optimize** service content based on product operations and will provide necessary notices within a reasonable scope.\n\n## 2. Account and Security\n\n1. You are responsible for all activity under your account and must **properly safeguard your account, password, and verification codes**.\n\n2. If you discover **abnormal account use, theft, or another security risk**, contact us promptly.\n\n## 3. Changes to This Agreement\n\nWe may **modify this Agreement** because of changes in laws or regulations, business adjustments, or service improvements. The updated Agreement takes effect when published. Continued use of COROS Products and Services means that you accept the updated Agreement." },
    { "name": "nav_fitness", "value": "Fitness" },
    { "name": "nav_records", "value": "Records" },
    { "name": "nav_explore", "value": "Explore" },
    { "name": "nav_me", "value": "Me" },
    { "name": "nav_unavailable", "value": "%s will be available in a future version" },
    { "name": "auth_error_auth_required", "value": "Please sign in first" },
    { "name": "auth_error_invalid_param", "value": "Enter complete and valid information" },
    { "name": "auth_error_account_exists", "value": "Account already exists" },
    { "name": "auth_error_account_not_found", "value": "Account not found" },
    { "name": "auth_error_password_incorrect", "value": "Incorrect password" },
    { "name": "auth_error_new_password_same_as_old", "value": "The new password must differ from the old password" },
    { "name": "auth_error_verify_code_invalid", "value": "Invalid verification code" },
    { "name": "auth_error_verify_code_expired", "value": "The verification code expired. Request a new one" },
    { "name": "auth_error_empty_data", "value": "No local account data" },
    { "name": "auth_error_corrupted_data", "value": "Local sign-in data is corrupted" },
    { "name": "auth_error_persist_failed", "value": "Failed to save the local sign-in state" },
    { "name": "auth_error_region_required", "value": "Select a registration region" },
    { "name": "auth_validation_account_required", "value": "Enter your account" },
    { "name": "auth_validation_password_required", "value": "Enter your password" },
    { "name": "auth_validation_password_length", "value": "Password must be 6-20 characters" },
    { "name": "auth_validation_phone_invalid", "value": "Enter an 11-digit phone number" },
    { "name": "auth_validation_email_invalid", "value": "Enter a valid email address" },
    { "name": "auth_validation_verify_code_required", "value": "Enter the verification code" },
    { "name": "auth_validation_password_alphanumeric_only", "value": "Password may contain only letters and numbers" },
    { "name": "auth_validation_password_letter_and_digit", "value": "Password must contain both letters and numbers" },
    { "name": "auth_validation_password_mismatch", "value": "Passwords do not match" },
    { "name": "auth_validation_register_incomplete", "value": "Enter account, password, region, and verification code" },
    { "name": "auth_validation_login_incomplete", "value": "Enter account and password" },
    { "name": "health_summary_activity_detail", "value": "%s km · Pace %s" },
    { "name": "health_visual_activity_easy_run", "value": "Easy run" },
    { "name": "health_visual_workout_easy_run", "value": "Easy run 10 km" },
    { "name": "health_visual_assessment_efficient", "value": "Efficient" },
    { "name": "health_visual_assessment_efficient_detail", "value": "Your load is improving fitness efficiently. Maintain a steady recovery rhythm." },
    { "name": "health_visual_cycling_climber", "value": "Climber" },
    { "name": "health_visual_activity_tempo_run", "value": "Tempo run" },
    { "name": "health_visual_assessment_overload", "value": "Overload" },
    { "name": "health_visual_assessment_overload_detail", "value": "Short-term load is high. Reduce intensity and prioritize recovery." },
    { "name": "health_visual_cycling_beginner", "value": "Beginner" },
    { "name": "health_unit_kilometers", "value": "km" },
    { "name": "health_visual_activity_pace", "value": "%s" },
    { "name": "health_visual_training_load_short", "value": "Training load" },
    { "name": "health_unit_minutes_long", "value": "min" },
    { "name": "health_visual_recommended_range", "value": "Recommended %s–%s" },
    { "name": "health_visual_short_term_load", "value": "Short-term load" },
    { "name": "health_visual_long_term_load", "value": "Long-term load" },
    { "name": "health_visual_load_ratio", "value": "Load ratio" },
    { "name": "health_unit_percent", "value": "%" },
    { "name": "health_visual_recovery_after_hours", "value": "Full recovery in about %s h" },
    { "name": "health_visual_marathon_prediction", "value": "Marathon prediction %s" },
    { "name": "health_unit_bpm", "value": "bpm" },
    { "name": "health_visual_average_heart_rate", "value": "Average heart rate" },
    { "name": "health_visual_average_stress", "value": "Average stress" },
    { "name": "health_unit_hours_short", "value": "h" },
    { "name": "health_unit_minutes_short", "value": "min" },
    { "name": "health_unit_milliseconds", "value": "ms" },
    { "name": "health_visual_hrv_low", "value": "Below balanced range" },
    { "name": "health_visual_hrv_balanced", "value": "Within balanced range" },
    { "name": "health_visual_hrv_average", "value": "Average %s ms" },
    { "name": "health_visual_measured_at", "value": "Measured at %s" },
    { "name": "health_visual_thirty_day_average", "value": "30-day average %s" },
    { "name": "health_visual_heart_rate", "value": "Heart rate" },
    { "name": "health_visual_hrv", "value": "HRV" },
    { "name": "health_visual_stress", "value": "Stress" },
    { "name": "health_visual_respiratory_rate", "value": "Respiratory rate" },
    { "name": "health_unit_per_minute", "value": "/min" },
    { "name": "health_visual_blood_oxygen", "value": "Blood oxygen" },
    { "name": "health_unit_kilograms", "value": "kg" },
    { "name": "health_visual_weight", "value": "Weight" },
    { "name": "health_visual_measured_date", "value": "Measured %s" },
    { "name": "health_visual_muscle_chest", "value": "Chest" },
    { "name": "health_visual_muscle_quadriceps", "value": "Quadriceps" },
    { "name": "health_visual_day_mon", "value": "M" },
    { "name": "health_visual_day_tue", "value": "T" },
    { "name": "health_visual_day_wed", "value": "W" },
    { "name": "health_visual_day_thu", "value": "T" },
    { "name": "health_visual_day_fri", "value": "F" },
    { "name": "health_visual_day_sat", "value": "S" },
    { "name": "health_visual_day_sun", "value": "S" }
  ]
}
